ampform/__init__.py
ampform/_qrules.py
ampform/py.typed
ampform/version.py
ampform/dynamics/__init__.py
ampform/dynamics/builder.py
ampform/dynamics/form_factor.py
ampform/dynamics/kmatrix.py
ampform/dynamics/phasespace.py
ampform/helicity/__init__.py
ampform/helicity/decay.py
ampform/helicity/naming.py
ampform/helicity/align/__init__.py
ampform/helicity/align/_spin.py
ampform/helicity/align/axisangle.py
ampform/helicity/align/dpd.py
ampform/io/__init__.py
ampform/kinematics/__init__.py
ampform/kinematics/angles.py
ampform/kinematics/lorentz.py
ampform/kinematics/phasespace.py
ampform/sympy/__init__.py
ampform/sympy/_array_expressions.py
ampform/sympy/_cache.py
ampform/sympy/_decorator.py
ampform/sympy/cached.py
ampform/sympy/deprecated.py
ampform/sympy/math.py
ampform-0.15.9.dist-info/licenses/LICENSE
symplot/__init__.py
symplot/py.typed
ampform-0.15.9.dist-info/METADATA
ampform-0.15.9.dist-info/WHEEL
ampform-0.15.9.dist-info/top_level.txt
ampform-0.15.9.dist-info/RECORD
