Metadata-Version: 2.4
Name: ampform
Version: 0.15.9
Summary: Automatically generate symbolic amplitude models for Partial Wave Analysis
Author-email: Common Partial Wave Analysis <compwa-admin@ep1.rub.de>
Maintainer-email: compwa-admin@ep1.rub.de
License:                                  Apache License
Project-URL: Changelog, https://github.com/ComPWA/ampform/releases
Project-URL: Documentation, https://ampform.rtfd.io
Project-URL: Source, https://github.com/ComPWA/ampform
Project-URL: Tracker, https://github.com/ComPWA/ampform/issues
Keywords: HEP,PWA,amplitude analysis,partial wave analysis,particle physics,particles,physics
Classifier: Development Status :: 4 - Beta
Classifier: Intended Audience :: Developers
Classifier: Intended Audience :: Education
Classifier: Intended Audience :: Science/Research
Classifier: License :: OSI Approved :: Apache Software License
Classifier: Natural Language :: English
Classifier: Operating System :: OS Independent
Classifier: Programming Language :: Python :: 3.10
Classifier: Programming Language :: Python :: 3.11
Classifier: Programming Language :: Python :: 3.12
Classifier: Programming Language :: Python :: 3.13
Classifier: Programming Language :: Python :: 3.9
Classifier: Programming Language :: Python
Classifier: Topic :: Scientific/Engineering :: Physics
Classifier: Topic :: Scientific/Engineering
Classifier: Typing :: Typed
Requires-Python: >=3.9
License-File: LICENSE
Requires-Dist: attrs>=20.1.0
Requires-Dist: frozendict
Requires-Dist: qrules>=0.9.6
Requires-Dist: sympy>=1.10
Provides-Extra: scipy
Requires-Dist: scipy; extra == "scipy"
Provides-Extra: viz
Requires-Dist: graphviz; extra == "viz"
Dynamic: license-file
